<?xml version="1.0"?>
<!DOCTYPE comps PUBLIC "-//Red Hat, Inc.//DTD Comps info//EN" "comps.dtd">
<comps>
  <!--  <meta> -->
  <!-- Meta information will go here eventually -->
  <!--  </meta> -->
  <group>
    <id>katello-server</id>
    <name>Katello Server</name>
    <description>Katello Server Packages</description>
    <uservisible>true</uservisible>
    <packagelist>
      <!-- katello core packages -->
      <packagereq type="default">foreman-proxy-content</packagereq>
      <packagereq type="default">katello</packagereq>
      <packagereq type="default">katello-client-bootstrap</packagereq>
      <packagereq type="default">katello-common</packagereq>
      <packagereq type="default">katello-debug</packagereq>
      <packagereq type="default">katello-repos</packagereq>
      <packagereq type="default">katello-repos-testing</packagereq>
      <packagereq type="default">katello-selinux</packagereq>
      <packagereq type="default">katello-utils</packagereq>
      <packagereq type="default">python-gofer</packagereq>
      <packagereq type="default">python-gofer-qpid</packagereq>
      <packagereq type="default">tfm-rubygem-activerecord-import</packagereq>
      <packagereq type="default">tfm-rubygem-ethon</packagereq>
      <packagereq type="default">tfm-rubygem-foreman_virt_who_configure</packagereq>
      <packagereq type="default">tfm-rubygem-hammer_cli_foreman_virt_who_configure</packagereq>
      <packagereq type="default">tfm-rubygem-hammer_cli_import</packagereq>
      <packagereq type="default">tfm-rubygem-hammer_cli_katello</packagereq>
      <packagereq type="default">tfm-rubygem-katello</packagereq>
      <packagereq type="default">tfm-rubygem-katello-assets</packagereq>
      <!-- katello thirdparty nodejs packages -->
      <packagereq type="default">tfm-nodejs-angular</packagereq>
      <packagereq type="default">tfm-nodejs-bootstrap-select</packagereq>
      <packagereq type="default">tfm-nodejs-decode-uri-component</packagereq>
      <packagereq type="default">tfm-nodejs-downshift</packagereq>
      <packagereq type="default">tfm-nodejs-ngreact</packagereq>
      <packagereq type="default">tfm-nodejs-query-string</packagereq>
      <packagereq type="default">tfm-nodejs-react-helmet</packagereq>
      <packagereq type="default">tfm-nodejs-strict-uri-encode</packagereq>
      <!-- katello thirdparty rubygem packages -->
      <packagereq type="default">tfm-rubygem-anemone</packagereq>
      <packagereq type="default">tfm-rubygem-ansi</packagereq>
      <packagereq type="default">tfm-rubygem-chunky_png</packagereq>
      <packagereq type="default">tfm-rubygem-foreman_rh_cloud</packagereq>
      <packagereq type="default">tfm-rubygem-foreman_scc_manager</packagereq>
      <packagereq type="default">tfm-rubygem-fssm</packagereq>
      <packagereq type="default">tfm-rubygem-fx</packagereq>
      <packagereq type="default">tfm-rubygem-hammer_cli_csv</packagereq>
      <packagereq type="default">tfm-rubygem-hammer_cli_foreman_scc_manager</packagereq>
      <packagereq type="default">tfm-rubygem-hpricot</packagereq>
      <packagereq type="default">tfm-rubygem-i18n_data</packagereq>
      <packagereq type="default">tfm-rubygem-justified</packagereq>
      <packagereq type="default">tfm-rubygem-pulpcore_client</packagereq>
      <packagereq type="default">tfm-rubygem-pulp_ansible_client</packagereq>
      <packagereq type="default">tfm-rubygem-pulp_certguard_client</packagereq>
      <packagereq type="default">tfm-rubygem-pulp_container_client</packagereq>
      <packagereq type="default">tfm-rubygem-pulp_deb_client</packagereq>
      <packagereq type="default">tfm-rubygem-pulp_file_client</packagereq>
      <packagereq type="default">tfm-rubygem-pulp_python_client</packagereq>
      <packagereq type="default">tfm-rubygem-pulp_rpm_client</packagereq>
      <packagereq type="default">tfm-rubygem-qpid_proton</packagereq>
      <packagereq type="default">tfm-rubygem-robotex</packagereq>
      <packagereq type="default">tfm-rubygem-runcible</packagereq>
      <packagereq type="default">tfm-rubygem-sexp_processor</packagereq>
      <packagereq type="default">tfm-rubygem-stomp</packagereq>
      <packagereq type="default">tfm-rubygem-typhoeus</packagereq>
      <packagereq type="default">tfm-rubygem-zest</packagereq>
      <!-- other katello related packages -->
      <packagereq type="default">rhel8-kickstart-setup</packagereq>
    </packagelist>
  </group>
  <group>
    <id>katello-server-docs</id>
    <name>Katello Server Documentation</name>
    <description>Katello Server Documentation Packages</description>
    <uservisible>true</uservisible>
    <packagelist>
      <packagereq type="optional">tfm-rubygem-foreman_rh_cloud-doc</packagereq>
      <packagereq type="optional">tfm-rubygem-foreman_scc_manager-doc</packagereq>
      <packagereq type="optional">tfm-rubygem-foreman_virt_who_configure-doc</packagereq>
      <packagereq type="default">tfm-rubygem-fx-doc</packagereq>
      <packagereq type="optional">tfm-rubygem-hpricot-doc</packagereq>
      <packagereq type="optional">tfm-rubygem-pulpcore_client-doc</packagereq>
      <packagereq type="optional">tfm-rubygem-pulp_ansible_client-doc</packagereq>
      <packagereq type="optional">tfm-rubygem-pulp_certguard_client-doc</packagereq>
      <packagereq type="optional">tfm-rubygem-pulp_container_client-doc</packagereq>
      <packagereq type="optional">tfm-rubygem-pulp_file_client-doc</packagereq>
      <packagereq type="optional">tfm-rubygem-pulp_python_client-doc</packagereq>
      <packagereq type="optional">tfm-rubygem-qpid_proton-doc</packagereq>
      <packagereq type="optional">tfm-rubygem-runcible-doc</packagereq>
      <packagereq type="optional">tfm-rubygem-sexp_processor-doc</packagereq>
      <packagereq type="optional">tfm-rubygem-stomp-doc</packagereq>
      <packagereq type="optional">tfm-rubygem-typhoeus-doc</packagereq>
      <packagereq type="optional">tfm-rubygem-zest-doc</packagereq>
    </packagelist>
  </group>
</comps>
